{
  "db": {
    "host": "localhost",
    "name": "dev"
  },
  "jwt": {
    "secret": "secret",
    "options": {
      "algorithm": "HS256"
    }
  },
  "bootstrap": {
    "User": [
      {"name": "Admin", "email": "admin@test.de", "password": "123456"},
      {"name": "Peter", "email": "peter@wunderlich.de", "password": "peter"},
      {"name": "Janus", "email": "janus@wunderlich.de", "password": "janus"},
      {"name": "Birte", "email": "birte@wunderlich.de", "password": "birte"},
      {"name": "Rosamunde", "email": "rosamunde@wunderlich.de", "password": "rosamunde"},
      {"name": "Waldi", "email": "waldi@wunderlich.de", "password": "waldi"}
    ]
  },
  "minio": {
    "key": "stimi-storage",
    "secret": "6!u40ws?}QwjhpFw",
    "bucket": "test"
  },
  "googleapi": {
    "GOOGLE_PLACES_API_KEY": "AIzaSyCK1nUagKpUd3I5i415iNaiXz5Cl2l9QM8",
    "GOOGLE_PLACES_OUTPUT_FORMAT": "json"
  }
}
